pycollitor/__init__.py
pycollitor/__main__.py
pycollitor/core.py
pycollitor/plugins/__init__.py
pycollitor/plugins/ansible_plugin.py
pycollitor/plugins/docker_plugin.py
pycollitor/plugins/kubernetes_plugin.py
pycollitor-0.1.1.dist-info/LICENSE
pycollitor-0.1.1.dist-info/METADATA
pycollitor-0.1.1.dist-info/WHEEL
pycollitor-0.1.1.dist-info/RECORD
