Metadata-Version: 2.1
Name: pycollitor
Version: 0.1.1
Summary: Collect tools data
License: MIT
Author: Rami BELGACEM
Author-email: ramibelgacem@gmail.com
Requires-Python: >=3.10,<4.0
Classifier: License :: OSI Approved :: MIT License
Classifier: Programming Language :: Python :: 3
Classifier: Programming Language :: Python :: 3.10
Classifier: Programming Language :: Python :: 3.11
Classifier: Programming Language :: Python :: 3.12
Requires-Dist: docker (>=6.1.3,<7.0.0)
